__init__.py
utils.py
vlei_verifier_client.py
vlei_verifier_client-1.0.1.dist-info/LICENSE
vlei_verifier_client-1.0.1.dist-info/METADATA
vlei_verifier_client-1.0.1.dist-info/WHEEL
vlei_verifier_client-1.0.1.dist-info/top_level.txt
vlei_verifier_client-1.0.1.dist-info/RECORD
