Metadata-Version: 2.2
Name: vlei-verifier-client
Version: 1.0.1
Summary: Python client for vlei-verifier
Home-page: https://github.com/GLEIF-IT/vlei-verifier-client-py
Author: Aidar Negimatzhanov
Author-email: aydar.negimatzhanov@perfectart.com
Classifier: Programming Language :: Python :: 3
Classifier: License :: OSI Approved :: MIT License
Classifier: Operating System :: OS Independent
Requires-Python: >=3.12
License-File: LICENSE
Requires-Dist: requests
Dynamic: author
Dynamic: author-email
Dynamic: classifier
Dynamic: description
Dynamic: description-content-type
Dynamic: home-page
Dynamic: requires-dist
Dynamic: requires-python
Dynamic: summary
